__init__.py
stringtemplate3/__init__.py
stringtemplate3/antlr.py
stringtemplate3/errors.py
stringtemplate3/grouploaders.py
stringtemplate3/groups.py
stringtemplate3/interfaces.py
stringtemplate3/templates.py
stringtemplate3/utils.py
stringtemplate3/writers.py
stringtemplate3/language/ASTExpr.py
stringtemplate3/language/ActionEvaluator.py
stringtemplate3/language/ActionLexer.py
stringtemplate3/language/ActionParser.py
stringtemplate3/language/AngleBracketTemplateLexer.py
stringtemplate3/language/CatIterator.py
stringtemplate3/language/ChunkToken.py
stringtemplate3/language/ConditionalExpr.py
stringtemplate3/language/DefaultTemplateLexer.py
stringtemplate3/language/Expr.py
stringtemplate3/language/FormalArgument.py
stringtemplate3/language/GroupLexer.py
stringtemplate3/language/GroupParser.py
stringtemplate3/language/InterfaceLexer.py
stringtemplate3/language/InterfaceParser.py
stringtemplate3/language/NewlineRef.py
stringtemplate3/language/StringRef.py
stringtemplate3/language/StringTemplateAST.py
stringtemplate3/language/StringTemplateToken.py
stringtemplate3/language/TemplateParser.py
stringtemplate3/language/__init__.py
stringtemplate3x-2023.11.2.dist-info/LICENSE
stringtemplate3x-2023.11.2.dist-info/LICENSE.bak
stringtemplate3x-2023.11.2.dist-info/METADATA
stringtemplate3x-2023.11.2.dist-info/WHEEL
stringtemplate3x-2023.11.2.dist-info/top_level.txt
stringtemplate3x-2023.11.2.dist-info/RECORD
