Metadata-Version: 2.1
Name: stringtemplate3x
Version: 2023.11.2
Summary: A wrapper for StringTemplate: a powerful template engine with strict model-view separation
Author-email: Terence Parr <parrt-spam@antlr.org>, Marq Kole <marq.kole-spam@philips.com>, Benjamin Niemann <pink-spam@odahoda.de>, Fredrick Eisele <fredrick.eisele@gmail.com>
Maintainer-email: Fredrick Eisele <fredrick.eisele@gmail.com>
Project-URL: Homepage, https://www.stringtemplate.org/
Project-URL: Bug Reports, https://github.com/phreed/stringtemplate3/issues
Project-URL: Source, https://github.com/phreed/stringtemplate3
Classifier: Programming Language :: Python :: 3
Classifier: Operating System :: OS Independent
Classifier: Development Status :: 2 - Pre-Alpha
Classifier: Intended Audience :: Developers
Classifier: License :: OSI Approved :: BSD License
Classifier: Topic :: Software Development :: Libraries :: Python Modules
Classifier: Topic :: Text Processing
Requires-Python: >=3.8
License-File: LICENSE
License-File: LICENSE.bak
